{
  "project_info": {
    "project_number": "667846412743",
    "project_id": "eventsy-f9d80",
    "storage_bucket": "eventsy-f9d80.appspot.com"
  },
  "client": [
    {
      "client_info": {
        "mobilesdk_app_id": "1:667846412743:android:1eb8d455c5c8bcd6bbb1e2",
        "android_client_info": {
          "package_name": "com.example.eventsy"
        }
      },
      "oauth_client": [
        {
          "client_id": "667846412743-3bishrhvsfd9s4vu0qhad881ln7re13e.apps.googleusercontent.com",
          "client_type": 3
        }
      ],
      "api_key": [
        {
          "current_key": "AIzaSyDf7lr7G6st7iLA7umMqJ9epMcIXKt-S8A"
        }
      ],
      "services": {
        "appinvite_service": {
          "other_platform_oauth_client": [
            {
              "client_id": "667846412743-3bishrhvsfd9s4vu0qhad881ln7re13e.apps.googleusercontent.com",
              "client_type": 3
            }
          ]
        }
      }
    }
  ],
  "configuration_version": "1"
}